lano_valo_py/__init__.py
lano_valo_py/based_api.py
lano_valo_py/exeptions.py
lano_valo_py/game_api.py
lano_valo_py/game_stats.py
lano_valo_py/henrik_api.py
lano_valo_py/lanologger.py
lano_valo_py/lanovalopy.py
lano_valo_py/utils/__init__.py
lano_valo_py/utils/const.py
lano_valo_py/utils/responce_helper.py
lano_valo_py/utils/types.py
lano_valo_py/valo_types/__init__.py
lano_valo_py/valo_types/valo_enums/__init__.py
lano_valo_py/valo_types/valo_enums/episodes.py
lano_valo_py/valo_types/valo_enums/general.py
lano_valo_py/valo_types/valo_enums/locales.py
lano_valo_py/valo_types/valo_enums/regions.py
lano_valo_py/valo_types/valo_enums/versions.py
lano_valo_py/valo_types/valo_models/__init__.py
lano_valo_py/valo_types/valo_models/account.py
lano_valo_py/valo_types/valo_models/content.py
lano_valo_py/valo_types/valo_models/crosshair.py
lano_valo_py/valo_types/valo_models/esports.py
lano_valo_py/valo_types/valo_models/game_agents_content.py
lano_valo_py/valo_types/valo_models/game_border_levels.py
lano_valo_py/valo_types/valo_models/game_gear.py
lano_valo_py/valo_types/valo_models/game_maps_content.py
lano_valo_py/valo_types/valo_models/game_weapons.py
lano_valo_py/valo_types/valo_models/general.py
lano_valo_py/valo_types/valo_models/leaderboard.py
lano_valo_py/valo_types/valo_models/match.py
lano_valo_py/valo_types/valo_models/mmr.py
lano_valo_py/valo_types/valo_models/mmr_stored_history.py
lano_valo_py/valo_types/valo_models/player_content.py
lano_valo_py/valo_types/valo_models/premier.py
lano_valo_py/valo_types/valo_models/raw.py
lano_valo_py/valo_types/valo_models/status.py
lano_valo_py/valo_types/valo_models/store.py
lano_valo_py/valo_types/valo_models/stored_matches.py
lano_valo_py/valo_types/valo_models/version.py
lano_valo_py/valo_types/valo_models/website.py
lano_valo_py/valo_types/valo_responses/__init__.py
lano_valo_py/valo_types/valo_responses/general.py
lano_valo_py/valo_types/valo_responses/match.py
lano_valo_py/valo_types/valo_responses/mmr.py
lanovalopy-1.1.0.dist-info/LICENSE.md
lanovalopy-1.1.0.dist-info/METADATA
lanovalopy-1.1.0.dist-info/WHEEL
lanovalopy-1.1.0.dist-info/RECORD
